README.md
setup.cfg
setup.py
ML_DL_implementation.egg-info/PKG-INFO
ML_DL_implementation.egg-info/SOURCES.txt
ML_DL_implementation.egg-info/dependency_links.txt
ML_DL_implementation.egg-info/requires.txt
ML_DL_implementation.egg-info/top_level.txt
MLlib/__init__.py
MLlib/activations.py
MLlib/autograd.py
MLlib/functional.py
MLlib/loss_func.py
MLlib/metrics.py
MLlib/models.py
MLlib/optimizers.py
MLlib/regularizer.py
MLlib/tensor.py