Metadata-Version: 2.1
Name: ML-DL-implementation
Version: 1.0.1
Summary: Package for ML and DL algorithms using nothing but numpy and matplotlib.
Home-page: https://github.com/RoboticsClubIITJ/ML-DL-implementation
Author: Robotics Society IITJ
Author-email: singh.77@iitj.ac.in
License: BSD-3
Download-URL: https://github.com/RoboticsClubIITJ/ML-DL-implementation/archive/refs/tags/1.0.1.tar.gz
Platform: UNKNOWN
Classifier: Programming Language :: Python :: 3
Classifier: License :: OSI Approved :: BSD License
Classifier: Operating System :: OS Independent
Requires-Python: >=3.6
